pytest_smartcollect/__init__.py
pytest_smartcollect/helpers.py
pytest_smartcollect/plugin.py
pytest_smartcollect-1.0.2.dist-info/METADATA
pytest_smartcollect-1.0.2.dist-info/RECORD
pytest_smartcollect-1.0.2.dist-info/WHEEL
pytest_smartcollect-1.0.2.dist-info/entry_points.txt
pytest_smartcollect-1.0.2.dist-info/top_level.txt
