Metadata-Version: 2.1
Name: pytest-smartcollect
Version: 1.0.2
Summary: A plugin for collecting tests that touch changed code
Home-page: https://github.com/vardaofthevalier/pytest-smartcollect
Author: Abigail Hahn
Author-email: abigail.n.hahn@gmail.com
Maintainer: Abigail Hahn
Maintainer-email: abigail.n.hahn@gmail.com
License: BSD-3
Requires-Dist: pytest (>=3.5.0)
Requires-Dist: GitPython (==2.1.11)
Requires-Dist: chardet (==3.0.4)
